LICENSE
MANIFEST.in
README.md
setup.py
tap_amplitude/__init__.py
tap_amplitude/connection.py
tap_amplitude/sync_strategies/__init__.py
tap_amplitude/sync_strategies/incremental.py
tests/.DS_Store
tests/test_discovery.py
tests/test_incremental_sync.py
tests/utils.py