Metadata-Version: 1.1
Name: tap-amplitude
Version: 0.0.3
Summary: Singer.io tap for extracting data from Amplitude via Snowflake
Home-page: https://singer.io
Author: Stitch
Author-email: UNKNOWN
License: UNKNOWN
Platform: UNKNOWN
Classifier: Programming Language :: Python :: 3 :: Only
